LICENSE.md
aiobiketrax/__init__.py
aiobiketrax/api.py
aiobiketrax/cli.py
aiobiketrax/client.py
aiobiketrax/consts.py
aiobiketrax/exceptions.py
aiobiketrax/models.py
aiobiketrax-1.3.1.dist-info/LICENSE.md
aiobiketrax-1.3.1.dist-info/METADATA
aiobiketrax-1.3.1.dist-info/WHEEL
aiobiketrax-1.3.1.dist-info/entry_points.txt
aiobiketrax-1.3.1.dist-info/RECORD
