Metadata-Version: 2.1
Name: aiobiketrax
Version: 1.3.1
Summary: Python library for interacting with the PowUnity BikeTrax GPS tracker.
Home-page: https://github.com/basilfx/aiobiketrax
License: MIT
Keywords: biketrax,powunity,asyncio,iot,gps
Author: Bas Stottelaar
Author-email: basstottelaar@gmail.com
Requires-Python: >=3.12,<4.0
Classifier: License :: OSI Approved :: MIT License
Classifier: Programming Language :: Python :: 3
Classifier: Programming Language :: Python :: 3.12
Requires-Dist: PyJWT (>=2.8.0,<3.0.0)
Requires-Dist: aiohttp (>=3.9.5,<4.0.0)
Requires-Dist: auth0-python (>=3.24.0,<4.0.0)
Requires-Dist: python-dateutil (>=2.9.0,<3.0.0)
Project-URL: Repository, https://github.com/basilfx/aiobiketrax
